ghga_message_schemas/__init__.py
ghga_message_schemas/schemas.py
ghga_message_schemas/json_schemas/__init__.py
ghga_message_schemas/json_schemas/drs_object_registered.json
ghga_message_schemas/json_schemas/file_internally_registered.json
ghga_message_schemas/json_schemas/file_staged_for_download.json
ghga_message_schemas/json_schemas/file_upload_received.json
ghga_message_schemas/json_schemas/new_study_created.json
ghga_message_schemas/json_schemas/non_staged_file_requested.json
tests/fixtures/__init__.py
tests/fixtures/utils.py
tests/unit/__init__.py
tests/unit/test_schema_validity.py
tests/unit/fixtures/__init__.py
tests/unit/fixtures/utils.py
ghga_message_schemas-0.3.1.dist-info/LICENSE
ghga_message_schemas-0.3.1.dist-info/METADATA
ghga_message_schemas-0.3.1.dist-info/WHEEL
ghga_message_schemas-0.3.1.dist-info/top_level.txt
ghga_message_schemas-0.3.1.dist-info/RECORD
