Metadata-Version: 2.1
Name: ghga-message-schemas
Version: 0.3.1
Summary: GHGA Message Schemas: A package that collects schemas used for messaging between GHGA service.
Home-page: https://github.com/ghga-de/ghga-message-schemas
Author: German Human Genome Phenome Archive (GHGA)
Author-email: contact@ghga.de
License: Apache 2.0
Platform: UNKNOWN
Classifier: Operating System :: POSIX :: Linux
Classifier: Programming Language :: Python :: 3.9
Classifier: License :: OSI Approved :: Apache Software License
Classifier: Topic :: Internet :: WWW/HTTP :: HTTP Servers
Classifier: Topic :: Scientific/Engineering :: Bio-Informatics
Requires-Python: >=3.9
License-File: LICENSE
Requires-Dist: jsonschema (==3.2.0)
Provides-Extra: all
Requires-Dist: pytest ; extra == 'all'
Requires-Dist: pytest-cov ; extra == 'all'
Requires-Dist: mypy ; extra == 'all'
Requires-Dist: pylint ; extra == 'all'
Requires-Dist: black ; extra == 'all'
Requires-Dist: flake8 ; extra == 'all'
Requires-Dist: isort ; extra == 'all'
Requires-Dist: bandit ; extra == 'all'
Requires-Dist: pre-commit ; extra == 'all'
Requires-Dist: requests ; extra == 'all'
Requires-Dist: mkdocs ; extra == 'all'
Requires-Dist: mkdocs-material ; extra == 'all'
Requires-Dist: mkdocstrings ; extra == 'all'
Requires-Dist: testcontainers ; extra == 'all'
Requires-Dist: typer ; extra == 'all'
Provides-Extra: dev
Requires-Dist: pytest ; extra == 'dev'
Requires-Dist: pytest-cov ; extra == 'dev'
Requires-Dist: mypy ; extra == 'dev'
Requires-Dist: pylint ; extra == 'dev'
Requires-Dist: black ; extra == 'dev'
Requires-Dist: flake8 ; extra == 'dev'
Requires-Dist: isort ; extra == 'dev'
Requires-Dist: bandit ; extra == 'dev'
Requires-Dist: pre-commit ; extra == 'dev'
Requires-Dist: requests ; extra == 'dev'
Requires-Dist: mkdocs ; extra == 'dev'
Requires-Dist: mkdocs-material ; extra == 'dev'
Requires-Dist: mkdocstrings ; extra == 'dev'
Requires-Dist: testcontainers ; extra == 'dev'
Requires-Dist: typer ; extra == 'dev'
